README.rst
setup.py
bin/stockholm_to_a3m
bin/stockholm_to_aln
bin/stockholm_to_fasta
stockholm_reformat/__init__.py
stockholm_reformat/creformat.c
stockholm_reformat/reformat.py
stockholm_reformat.egg-info/PKG-INFO
stockholm_reformat.egg-info/SOURCES.txt
stockholm_reformat.egg-info/dependency_links.txt
stockholm_reformat.egg-info/top_level.txt