Metadata-Version: 1.1
Name: stockholm-reformat
Version: 0.4.1
Summary: Fast Stockholm to other formats Multiple Sequence Alignment reformater.
Home-page: https://github.com/Dapid/stockholm_reformat
Author: David Menéndez Hurtado
Author-email: davidmenhur@gmail.com
License: BSD 3-clause
Platform: UNKNOWN
Classifier: Programming Language :: Python
Classifier: Programming Language :: Python :: 2
Classifier: Programming Language :: Python :: 3
Classifier: Programming Language :: Cython
Classifier: Programming Language :: Python :: Implementation :: CPython
Classifier: Topic :: Scientific/Engineering :: Bio-Informatics
Classifier: Intended Audience :: Science/Research
Classifier: Development Status :: 3 - Alpha
Classifier: License :: OSI Approved :: BSD License
